asce7_16/__init__.py
asce7_16/__version__
asce7_16/seismic.py
asce7_16-0.1.0.dist-info/LICENSE
asce7_16-0.1.0.dist-info/METADATA
asce7_16-0.1.0.dist-info/WHEEL
asce7_16-0.1.0.dist-info/top_level.txt
asce7_16-0.1.0.dist-info/RECORD
